archer/__init__.py
archer/_compat.py
archer/_server.py
archer/app.py
archer/cli.py
archer/config.py
archer/event.py
archer/helper.py
archer/logger.py
archer/test.py
archer-0.5.dist-info/DESCRIPTION.rst
archer-0.5.dist-info/entry_points.txt
archer-0.5.dist-info/METADATA
archer-0.5.dist-info/metadata.json
archer-0.5.dist-info/RECORD
archer-0.5.dist-info/top_level.txt
archer-0.5.dist-info/WHEEL
